embedize/__init__.py
embedize/dbs.py
embedize/dcore.py
embedize-1.0.2.dist-info/licenses/LICENSE
embedize-1.0.2.dist-info/METADATA
embedize-1.0.2.dist-info/WHEEL
embedize-1.0.2.dist-info/top_level.txt
embedize-1.0.2.dist-info/RECORD
