Metadata-Version: 2.4
Name: embedize
Version: 1.0.2
Summary: SQLite and DuckDB Tiny Lib
Home-page: https://github.com/asinerum/embedize
Author: Asinerum Conlang Project
Author-email: asinerum.com@gmail.com
License: MIT
Classifier: Programming Language :: Python :: 3
Classifier: License :: OSI Approved :: MIT License
Classifier: Operating System :: OS Independent
Requires-Python: >=3.7
License-File: LICENSE
Requires-Dist: duckdb>=1.4.2
Requires-Dist: pydantic>=2.12.5
Requires-Dist: pyyaml>=6.0.3
Dynamic: license-file
